cohesion/__init__.py
cohesion/calculations.py
cohesion/cohesion_pipeline.py
cohesion/empty.py
cohesion/formula.py
cohesion/utils.py
cohesion/zero_shot_classifier.py
cohesion_pipeline-0.1.2.dist-info/LICENSE.txt
cohesion_pipeline-0.1.2.dist-info/METADATA
cohesion_pipeline-0.1.2.dist-info/WHEEL
cohesion_pipeline-0.1.2.dist-info/top_level.txt
cohesion_pipeline-0.1.2.dist-info/RECORD
