Metadata-Version: 2.1
Name: cohesion-pipeline
Version: 0.1.2
Summary: Cohesion measurement to evaluate topic modeling score. call cohesion_df(df)
Home-page: https://github.com/Berdugo1994/cohesion-pipeline
Author: Eden Berdugo, Tom Nachman, Asaf Solomon
Author-email: berdugogo@gmail.com
Classifier: Programming Language :: Python :: 3
Classifier: License :: OSI Approved :: MIT License
Classifier: Operating System :: OS Independent
Requires-Python: ~=3.8
License-File: LICENSE.txt
Requires-Dist: nltk (~=3.7)
Requires-Dist: scikit-learn (~=1.1.1)
Requires-Dist: pandas (~=1.3.0)
Requires-Dist: transformers (~=4.20.1)
Requires-Dist: numpy (~=1.21.0)
Requires-Dist: tqdm (~=4.64.0)
Requires-Dist: tensorflow (~=2.9.1)
Requires-Dist: protobuf (~=3.9.2)
Requires-Dist: torch
